nautobot_dns_models/__init__.py
nautobot_dns_models/api/__init__.py
nautobot_dns_models/api/serializers.py
nautobot_dns_models/api/urls.py
nautobot_dns_models/api/views.py
nautobot_dns_models/app-config-schema.json
nautobot_dns_models/filter_extensions.py
nautobot_dns_models/filters.py
nautobot_dns_models/forms.py
nautobot_dns_models/graphql/types.py
nautobot_dns_models/migrations/0001_initial.py
nautobot_dns_models/migrations/0002_srvrecordmodel.py
nautobot_dns_models/migrations/0003_remove_aaaarecordmodel_ttl_remove_arecordmodel_ttl_and_more.py
nautobot_dns_models/migrations/0004_rename_aaaarecordmodel_aaaarecord_and_more.py
nautobot_dns_models/migrations/0005_dnsview_alter_dnszone_name_dnsviewprefixassignment_and_more.py
nautobot_dns_models/migrations/__init__.py
nautobot_dns_models/models.py
nautobot_dns_models/navigation.py
nautobot_dns_models/static/nautobot_dns_models/docs/404.html
nautobot_dns_models/static/nautobot_dns_models/docs/admin/compatibility_matrix.html
nautobot_dns_models/static/nautobot_dns_models/docs/admin/install.html
nautobot_dns_models/static/nautobot_dns_models/docs/admin/release_notes/index.html
nautobot_dns_models/static/nautobot_dns_models/docs/admin/release_notes/version_0.2.html
nautobot_dns_models/static/nautobot_dns_models/docs/admin/release_notes/version_1.0.html
nautobot_dns_models/static/nautobot_dns_models/docs/admin/release_notes/version_1.1.html
nautobot_dns_models/static/nautobot_dns_models/docs/admin/release_notes/version_1.2.html
nautobot_dns_models/static/nautobot_dns_models/docs/admin/release_notes/version_1.3.html
nautobot_dns_models/static/nautobot_dns_models/docs/admin/uninstall.html
nautobot_dns_models/static/nautobot_dns_models/docs/admin/upgrade.html
nautobot_dns_models/static/nautobot_dns_models/docs/assets/_mkdocstrings.css
nautobot_dns_models/static/nautobot_dns_models/docs/assets/extra.css
nautobot_dns_models/static/nautobot_dns_models/docs/assets/favicon.ico
nautobot_dns_models-1.3.1.dist-info/LICENSE
nautobot_dns_models-1.3.1.dist-info/METADATA
nautobot_dns_models-1.3.1.dist-info/WHEEL
nautobot_dns_models-1.3.1.dist-info/RECORD
