Metadata-Version: 2.3
Name: nautobot-dns-models
Version: 1.3.1
Summary: Nautobot DNS Models
License: Apache-2.0
Keywords: nautobot,nautobot-app,nautobot-plugin
Author: Network to Code, LLC
Author-email: info@networktocode.com
Requires-Python: >=3.10,<3.13
Classifier: Development Status :: 5 - Production/Stable
Classifier: Intended Audience :: Developers
Classifier: License :: OSI Approved :: Apache Software License
Classifier: Programming Language :: Python :: 3
Classifier: Programming Language :: Python :: 3.10
Classifier: Programming Language :: Python :: 3.11
Classifier: Programming Language :: Python :: 3.12
Provides-Extra: all
Requires-Dist: nautobot (>=2.4.20,<3.0.0)
Project-URL: Documentation, https://docs.nautobot.com/projects/nautobot-dns-models/en/latest/
Project-URL: Homepage, https://github.com/nautobot/nautobot-app-dns-models
Project-URL: Repository, https://github.com/nautobot/nautobot-app-dns-models
